{
  "questions": [
    {
      "id": 1,
      "question": "Офаридгор чӣ гуна олами ҳастиро офарид?",
      "options": [
        "Бо як калимаи 'Бош'",
        "Дар шаш рӯз",
        "Дар як лаҳза",
        "Бе ҳеч тадбир"
      ],
      "correctIndex": 1,
      "image": "https://play-lh.googleusercontent.com/rhAU-r-K1CJo5V8TqgjknLhjm_w0UN_GKebb8ouSApdq-SVW_tmGBtXVlhr1mRODugFTJCI7EwohmBo9shD05w=w240-h480-rw"
    },
    {
      "id": 2,
      "question": "Аввалин одам чӣ гуна офарида шуд?",
      "options": [
        "Аз хоки сафед, сиёҳ, сурх ва зард",
        "Аз оби дарё",
        "Аз оташи алангадор",
        "Аз боди сард"
      ],
      "correctIndex": 0,
      "image": "https://play-lh.googleusercontent.com/rhAU-r-K1CJo5V8TqgjknLhjm_w0UN_GKebb8ouSApdq-SVW_tmGBtXVlhr1mRODugFTJCI7EwohmBo9shD05w=w240-h480-rw"
    },
        {
      "id": 3,
      "question": "Шоҳнома бо ситоиши кӣ оғоз меёбад?",
      "options": [
        "Подшоҳон",
        "Паҳлавонон",
        "Офаридгор",
        "Донишмандон"
      ],
      "correctIndex": 2,
      "image": ""
    },
    {
      "id": 4,
      "question": "Муаллифи асари «Шоҳнома» кист?",
      "options": [
        "Рӯдакӣ",
        "Фирдавсӣ",
        "Саъдӣ",
        "Ҳофиз"
      ],
      "correctIndex": 1,
      "image": ""
    },
    {
      "id": 5,
      "question": "Аввалин подшоҳ дар Шоҳнома ки буд?",
      "options": [
        "Ҷамшед",
        "Каюмарс",
        "Заҳҳок",
        "Фаридун"
      ],
      "correctIndex": 1,
      "image": ""
    },
    {
      "id": 6,
      "question": "Каюмарс чӣ мақом дошт?",
      "options": [
        "Паҳлавон",
        "Паёмбар",
        "Аввалин подшоҳ",
        "Фармондеҳ"
      ],
      "correctIndex": 2,
      "image": ""
    },
    {
      "id": 7,
      "question": "Писари Каюмарс чӣ ном дошт?",
      "options": [
        "Сиёмак",
        "Ҳушанг",
        "Таҳмурас",
        "Ҷамшед"
      ],
      "correctIndex": 0,
      "image": ""
    },
    {
      "id": 8,
      "question": "Сиёмак дар ҷанг бо кӣ ҳалок шуд?",
      "options": [
        "Аждаҳо",
        "Деви сиёҳ",
        "Заҳҳок",
        "Афросиёб"
      ],
      "correctIndex": 1,
      "image": ""
    },
    {
      "id": 9,
      "question": "Кӣ қасоси Сиёмакро гирифт?",
      "options": [
        "Каюмарс",
        "Ҷамшед",
        "Ҳушанг",
        "Фаридун"
      ],
      "correctIndex": 2,
      "image": ""
    },
    {
      "id": 10,
      "question": "Ҳушанг бо кадом кашфиёт машҳур аст?",
      "options": [
        "Оташ",
        "Обёрӣ",
        "Хат",
        "Кишоварзӣ"
      ],
      "correctIndex": 0,
      "image": ""
    },
    {
      "id": 11,
      "question": "Кадом ид ба кашфи оташ вобаста аст?",
      "options": [
        "Наврӯз",
        "Меҳргон",
        "Сада",
        "Тиргон"
      ],
      "correctIndex": 2,
      "image": ""
    },
    {
      "id": 12,
      "question": "Пас аз Ҳушанг кӣ ба тахт нишаст?",
      "options": [
        "Каюмарс",
        "Таҳмурас",
        "Ҷамшед",
        "Фаридун"
      ],
      "correctIndex": 1,
      "image": ""
    },
    {
      "id": 13,
      "question": "Таҳмурас бо чӣ лақаб машҳур аст?",
      "options": [
        "Девбанд",
        "Оташофар",
        "Шоҳи одил",
        "Ҷаҳонгир"
      ],
      "correctIndex": 0,
      "image": ""
    },
    {
      "id": 14,
      "question": "Таҳмурас девонро барои чӣ мағлуб кард?",
      "options": [
        "Барои тилло",
        "Барои қудрат",
        "Барои дониш",
        "Барои интиқом"
      ],
      "correctIndex": 2,
      "image": ""
    },
    {
      "id": 15,
      "question": "Кадом подшоҳ давраи ободӣ ва пешрафтро овард?",
      "options": [
        "Заҳҳок",
        "Ҷамшед",
        "Фаридун",
        "Манучеҳр"
      ],
      "correctIndex": 1,
      "image": ""
    },
    {
      "id": 16,
      "question": "Ҷамшед кадом идро ҷорӣ кард?",
      "options": [
        "Сада",
        "Тиргон",
        "Наврӯз",
        "Меҳргон"
      ],
      "correctIndex": 2,
      "image": ""
    },
    {
      "id": 17,
      "question": "Чаро Ҷамшед аз тахт афтод?",
      "options": [
        "Аз ҷанг",
        "Аз беморӣ",
        "Аз кибру ғурур",
        "Аз пирӣ"
      ],
      "correctIndex": 2,
      "image": ""
    },
    {
      "id": 18,
      "question": "Кӣ пас аз суқути Ҷамшед ҳоким шуд?",
      "options": [
        "Фаридун",
        "Заҳҳок",
        "Манучеҳр",
        "Ҳушанг"
      ],
      "correctIndex": 1,
      "image": ""
    },
    {
      "id": 19,
      "question": "Заҳҳок аз куҷо пайдо шуд?",
      "options": [
        "Эрон",
        "Турон",
        "Араб",
        "Ҳинд"
      ],
      "correctIndex": 2,
      "image": ""
    },
    {
      "id": 20,
      "question": "Дар китфҳои Заҳҳок чӣ пайдо шуд?",
      "options": [
        "Шох",
        "Мор",
        "Пар",
        "Захм"
      ],
      "correctIndex": 1,
      "image": ""
    },
    {
      "id": 21,
      "question": "Заҳҳок ҳар рӯз барои морон чӣ мехост?",
      "options": [
        "Нон",
        "Хун",
        "Майнаи ҷавонҳо",
        "Гӯшт"
      ],
      "correctIndex": 2,
      "image": ""
    },
    {
      "id": 22,
      "question": "Кадом қаҳрамон Заҳҳокро мағлуб кард?",
      "options": [
        "Рустам",
        "Коваи оҳангар",
        "Фаридун",
        "Манучеҳр"
      ],
      "correctIndex": 2,
      "image": ""
    },    {
      "id": 23,
      "question": "Падари Заҳҳок чӣ кас буд?",
      "options": [
        "Подшоҳ",
        "Оҳангар",
        "Марди нек",
        "Марди бадкор"
      ],
      "correctIndex": 2,
      "image": ""
    },
    {
      "id": 24,
      "question": "Кӣ Заҳҳокро ба роҳи бад роҳнамоӣ кард?",
      "options": [
        "Фаридун",
        "Иблис",
        "Кова",
        "Ҷамшед"
      ],
      "correctIndex": 1,
      "image": ""
    },
    {
      "id": 25,
      "question": "Иблис Заҳҳокро ба куштани кӣ водор кард?",
      "options": [
        "Душманаш",
        "Падараш",
        "Бародарш",
        "Дӯсти наздик"
      ],
      "correctIndex": 1,
      "image": ""
    },
    {
      "id": 26,
      "question": "Пас аз бӯсаи Иблис дар китфи Заҳҳок чӣ рух дод?",
      "options": [
        "Захм пайдо шуд",
        "Мор рӯид",
        "Оташ баромад",
        "Хун ҷорӣ шуд"
      ],
      "correctIndex": 1,
      "image": ""
    },
    {
      "id": 27,
      "question": "Кӣ ба мардум бар зидди Заҳҳок қиём кард?",
      "options": [
        "Рустам",
        "Фаридун",
        "Коваи оҳангар",
        "Манучеҳр"
      ],
      "correctIndex": 2,
      "image": ""
    },
    {
      "id": 28,
      "question": "Коваи оҳангар чӣ чизро ҳамчун парчам истифода бурд?",
      "options": [
        "Либоси подшоҳӣ",
        "Дирафши чармӣ",
        "Сипар",
        "Парчами тиллоӣ"
      ],
      "correctIndex": 1,
      "image": ""
    },
    {
      "id": 29,
      "question": "Ин парчам баъдтар бо чӣ ном машҳур шуд?",
      "options": [
        "Парчами Эрон",
        "Дирафши Ковиёнӣ",
        "Алам",
        "Нишони подшоҳӣ"
      ],
      "correctIndex": 1,
      "image": ""
    },
    {
      "id": 30,
      "question": "Фаридун дар кӯдакӣ дар куҷо пинҳон карда шуд?",
      "options": [
        "Дар қаср",
        "Дар кӯҳ",
        "Назди чӯпон",
        "Дар шаҳр"
      ],
      "correctIndex": 2,
      "image": ""
    },
    {
      "id": 31,
      "question": "Кӣ Фаридунро бо шири худ калон кард?",
      "options": [
        "Модараш",
        "Гов",
        "Малика",
        "Чӯпон"
      ],
      "correctIndex": 1,
      "image": ""
    },
    {
      "id": 32,
      "question": "Номи гове, ки Фаридунро шир дод, чӣ буд?",
      "options": [
        "Савор",
        "Порой",
        "Бармоя",
        "Симурғ"
      ],
      "correctIndex": 2,
      "image": ""
    },
    {
      "id": 33,
      "question": "Заҳҳок бо гов Бармоя чӣ кард?",
      "options": [
        "Озод кард",
        "Кушт",
        "Фурӯхт",
        "Рабуд"
      ],
      "correctIndex": 1,
      "image": ""
    },
    {
      "id": 34,
      "question": "Фаридун бо кадом силоҳ Заҳҳокро мағлуб кард?",
      "options": [
        "Шамшер",
        "Гурз",
        "Найза",
        "Тир"
      ],
      "correctIndex": 1,
      "image": ""
    },
    {
      "id": 35,
      "question": "Фаридун Заҳҳокро кушт ё зиндонӣ кард?",
      "options": [
        "Кушт",
        "Озод кард",
        "Зиндонӣ кард",
        "Бадарға кард"
      ],
      "correctIndex": 2,
      "image": ""
    },
    {
      "id": 36,
      "question": "Заҳҳок дар куҷо ба занҷир баста шуд?",
      "options": [
        "Дар қаср",
        "Дар кӯҳи Дамованд",
        "Дар биёбон",
        "Дар шаҳр"
      ],
      "correctIndex": 1,
      "image": ""
    },
    {
      "id": 37,
      "question": "Фаридун чанд писар дошт?",
      "options": [
        "Ду",
        "Се",
        "Чор",
        "Як"
      ],
      "correctIndex": 1,
      "image": ""
    },
    {
      "id": 38,
      "question": "Номҳои писарони Фаридун кадомҳоянд?",
      "options": [
        "Салм, Тур, Ираж",
        "Рустам, Суҳроб, Зол",
        "Манучеҳр, Қубод, Кайқубод",
        "Ҳушанг, Таҳмурас, Ҷамшед"
      ],
      "correctIndex": 0,
      "image": ""
    },
    {
      "id": 39,
      "question": "Фаридун ҷаҳонро байни писаронаш чӣ гуна тақсим кард?",
      "options": [
        "Ба таври баробар",
        "Ба қавӣтарин дод",
        "Ба хурдӣ дод",
        "Ба одилона тақсим кард"
      ],
      "correctIndex": 3,
      "image": ""
    },
    {
      "id": 40,
      "question": "Кадом писари Фаридун кушта шуд?",
      "options": [
        "Салм",
        "Тур",
        "Ираж",
        "Манучеҳр"
      ],
      "correctIndex": 2,
      "image": ""
    },
    {
      "id": 41,
      "question": "Кӣ қасоси Иражро гирифт?",
      "options": [
        "Фаридун",
        "Манучеҳр",
        "Рустам",
        "Кова"
      ],
      "correctIndex": 1,
      "image": ""
    },
    {
      "id": 42,
      "question": "Манучеҳр аз насли кӣ буд?",
      "options": [
        "Салм",
        "Тур",
        "Ираж",
        "Заҳҳок"
      ],
      "correctIndex": 2,
      "image": ""
    },    {
      "id": 43,
      "question": "Кӣ зидди Тур ҷангид?",
      "options": [
        "Салм",
        "Ираж",
        "Фаридун",
        "Манучеҳр"
      ],
      "correctIndex": 2,
      "image": ""
    },
    {
      "id": 44,
      "question": "Пас аз марги Ираж, Тур чӣ кард?",
      "options": [
        "Покиза монд",
        "Ҷангро идома дод",
        "Бародарашро кушт",
        "Шаҳрҳоро фишор дод"
      ],
      "correctIndex": 1,
      "image": ""
    },
    {
      "id": 45,
      "question": "Кӣ қудратро ба даст гирифт, пас аз марги Фаридун?",
      "options": [
        "Манучеҳр",
        "Салм",
        "Тур",
        "Рустам"
      ],
      "correctIndex": 0,
      "image": ""
    },
    {
      "id": 46,
      "question": "Манучеҳр асосан бо кӣ мухолифат дошт?",
      "options": [
        "Эрониён",
        "Турониён",
        "Рустам",
        "Заҳҳок"
      ],
      "correctIndex": 1,
      "image": ""
    },
    {
      "id": 47,
      "question": "Рустам аз кадом шаҳр буд?",
      "options": [
        "Бобил",
        "Самарқанд",
        "Сисонӣ",
        "Дамғо"
      ],
      "correctIndex": 2,
      "image": ""
    },
    {
      "id": 48,
      "question": "Кӣ Рустамро ҳамчун шӯришиён хондааст?",
      "options": [
        "Фаридун",
        "Манучеҳр",
        "Тур",
        "Ираж"
      ],
      "correctIndex": 1,
      "image": ""
    },
    {
      "id": 49,
      "question": "Рустам кӣ буд?",
      "options": [
        "Подшоҳ",
        "Паҳлавон",
        "Паёмбар",
        "Фармондеҳ"
      ],
      "correctIndex": 1,
      "image": ""
    },
    {
      "id": 50,
      "question": "Кӣ аз падари Рустам ҳимоят кард?",
      "options": [
        "Иращ",
        "Зал",
        "Манучеҳр",
        "Ҳушанг"
      ],
      "correctIndex": 1,
      "image": ""
    },
    {
      "id": 51,
      "question": "Номи парандаи бузург ва афсонавии Рустам чӣ буд?",
      "options": [
        "Симурғ",
        "Перун",
        "Гург",
        "Боз"
      ],
      "correctIndex": 0,
      "image": ""
    },
    {
      "id": 52,
      "question": "Симурғ ба Рустам чӣ ёрӣ дод?",
      "options": [
        "Нақлиёт",
        "Шифо",
        "Нақшаи ҷангӣ",
        "Тамрин"
      ],
      "correctIndex": 2,
      "image": ""
    },
    {
      "id": 53,
      "question": "Рустам бо кӣ дӯст буд?",
      "options": [
        "Заҳҳок",
        "Кова",
        "Иращ",
        "Фаридун"
      ],
      "correctIndex": 2,
      "image": ""
    },
    {
      "id": 54,
      "question": "Зал падари Рустам аз куҷо омад?",
      "options": [
        "Сисонӣ",
        "Бирюн",
        "Кӯҳҳои Суғд",
        "Дашт"
      ],
      "correctIndex": 0,
      "image": ""
    },
    {
      "id": 55,
      "question": "Рустам дар кадом синф омӯхт?",
      "options": [
        "Ҷанг",
        "Шербозӣ",
        "Сиёсат",
        "Ҳарсеяш"
      ],
      "correctIndex": 3,
      "image": ""
    },
    {
      "id": 56,
      "question": "Кӣ ба ҷанги Рустам ва Тур баҳои аҳамият дод?",
      "options": [
        "Манучеҳр",
        "Ираж",
        "Зал",
        "Фаридун"
      ],
      "correctIndex": 0,
      "image": ""
    },
    {
      "id": 57,
      "question": "Рустам ва Тур дар куҷо рӯбарӯ шуданд?",
      "options": [
        "Дар саҳро",
        "Дар кӯҳ",
        "Дар шаҳр",
        "Дар дарёи бузург"
      ],
      "correctIndex": 0,
      "image": ""
    },
    {
      "id": 58,
      "question": "Рустам Турро кӣ гирифт?",
      "options": [
        "Дар ҷанг",
        "Дар фирор",
        "Дар задухӯрӣ",
        "Ба воситаи найза"
      ],
      "correctIndex": 2,
      "image": ""
    },
    {
      "id": 59,
      "question": "Пас аз куштани Тур, Рустам чӣ кард?",
      "options": [
        "Баргашт",
        "Боз ҷангид",
        "Подшоҳ шуд",
        "Печид"
      ],
      "correctIndex": 0,
      "image": ""
    },
    {
      "id": 60,
      "question": "Рустам дар ғам кардани кӣ машҳур аст?",
      "options": [
        "Суҳроб",
        "Таҳмурас",
        "Ҷамшед",
        "Манучеҳр"
      ],
      "correctIndex": 0,
      "image": ""
    },
    {
      "id": 61,
      "question": "Суҳроб писари кӣ буд?",
      "options": [
        "Рустам",
        "Манучеҳр",
        "Зал",
        "Ираж"
      ],
      "correctIndex": 0,
      "image": ""
    },
    {
      "id": 62,
      "question": "Рустам ва Суҳроб бо ҳам ҷангиданд?",
      "options": [
        "Бале",
        "Не",
        "Ҳаёт танҳо",
        "Бо Сайёра"
      ],
      "correctIndex": 1,
      "image": ""
    },    {
      "id": 63,
      "question": "Зал дар кӯдакӣ чаро аз падар ҷудо шуд?",
      "options": [
        "Аз ҷанг",
        "Аз беморӣ",
        "Аз ранги сафеди мӯяш",
        "Аз сафар"
      ],
      "correctIndex": 2,
      "image": ""
    },
    {
      "id": 64,
      "question": "Кӣ Залро дар кӯҳ нигоҳубин кард?",
      "options": [
        "Гов",
        "Симурғ",
        "Чӯпон",
        "Фаридун"
      ],
      "correctIndex": 1,
      "image": ""
    },
    {
      "id": 65,
      "question": "Падари Зал чӣ ном дошт?",
      "options": [
        "Манучеҳр",
        "Сам",
        "Наримон",
        "Қубод"
      ],
      "correctIndex": 1,
      "image": ""
    },
    {
      "id": 66,
      "question": "Сам чӣ гуна фаҳмид, ки Зал зинда аст?",
      "options": [
        "Хоб дид",
        "Паём гирифт",
        "Симурғ хабар дод",
        "Мардум гуфтанд"
      ],
      "correctIndex": 0,
      "image": ""
    },
    {
      "id": 67,
      "question": "Симурғ ҳангоми ҷудоӣ ба Зал чӣ дод?",
      "options": [
        "Шамшер",
        "Гурз",
        "Пари худ",
        "Тилло"
      ],
      "correctIndex": 2,
      "image": ""
    },
    {
      "id": 68,
      "question": "Зал бо кадом зан издивоҷ кард?",
      "options": [
        "Рудоба",
        "Таҳмина",
        "Фарангис",
        "Синдухт"
      ],
      "correctIndex": 0,
      "image": ""
    },
    {
      "id": 69,
      "question": "Рудоба духтари кӣ буд?",
      "options": [
        "Сам",
        "Меҳроб",
        "Манучеҳр",
        "Фаридун"
      ],
      "correctIndex": 1,
      "image": ""
    },
    {
      "id": 70,
      "question": "Манучеҳр дар оғоз ба издивоҷи Зал ва Рудоба чӣ назар дошт?",
      "options": [
        "Розӣ буд",
        "Мухолиф буд",
        "Бетафовут буд",
        "Хабар надошт"
      ],
      "correctIndex": 1,
      "image": ""
    },
    {
      "id": 71,
      "question": "Кӣ Манучеҳрро ба розигӣ овард?",
      "options": [
        "Сам",
        "Зал",
        "Синдухт",
        "Рудоба"
      ],
      "correctIndex": 2,
      "image": ""
    },
    {
      "id": 72,
      "question": "Таваллуди Рустам бо чӣ душворӣ ҳамроҳ буд?",
      "options": [
        "Ҷанг",
        "Беморӣ",
        "Таваллуди сахт",
        "Сафар"
      ],
      "correctIndex": 2,
      "image": ""
    },
    {
      "id": 73,
      "question": "Кӣ ба Зал роҳи наҷоти Рудобаро омӯзонд?",
      "options": [
        "Сам",
        "Симурғ",
        "Манучеҳр",
        "Чӯпон"
      ],
      "correctIndex": 1,
      "image": ""
    },
    {
      "id": 74,
      "question": "Бо кадом роҳ Рустам ба дунё омад?",
      "options": [
        "Одатӣ",
        "Бо ҷоду",
        "Ба буриши шикам",
        "Бо дуо"
      ],
      "correctIndex": 2,
      "image": ""
    },
    {
      "id": 75,
      "question": "Ин навъи таваллуд бо чӣ ном машҳур шуд?",
      "options": [
        "Таваллуди одӣ",
        "Рустамзода",
        "Таваллуди қаҳрамон",
        "Кайонӣ"
      ],
      "correctIndex": 1,
      "image": ""
    },
    {
      "id": 76,
      "question": "Рустам дар кӯдакӣ бо чӣ фарқ мекард?",
      "options": [
        "Зебоӣ",
        "Қувваи фавқулода",
        "Зиракӣ",
        "Оромӣ"
      ],
      "correctIndex": 1,
      "image": ""
    },
    {
      "id": 77,
      "question": "Аспи машҳури Рустам чӣ ном дошт?",
      "options": [
        "Бармоя",
        "Шабдиз",
        "Рахш",
        "Симурғ"
      ],
      "correctIndex": 2,
      "image": ""
    },
    {
      "id": 78,
      "question": "Рахш бо чӣ хусусият машҳур буд?",
      "options": [
        "Суръат",
        "Қувва ва вафо",
        "Зебоӣ",
        "Ранг"
      ],
      "correctIndex": 1,
      "image": ""
    },
    {
      "id": 79,
      "question": "Рустам аввалин корномаи бузурги худро кай анҷом дод?",
      "options": [
        "Дар кӯдакӣ",
        "Дар ҷавонӣ",
        "Дар пирӣ",
        "Пас аз подшоҳ шудан"
      ],
      "correctIndex": 1,
      "image": ""
    },
    {
      "id": 80,
      "question": "Рустам бештар ҳимоятгари кадом кишвар буд?",
      "options": [
        "Турон",
        "Араб",
        "Эрон",
        "Ҳинд"
      ],
      "correctIndex": 2,
      "image": ""
    },
    {
      "id": 81,
      "question": "Насли Рустам ба кӣ мерасад?",
      "options": [
        "Фаридун",
        "Сам ва Наримон",
        "Заҳҳок",
        "Манучеҳр"
      ],
      "correctIndex": 1,
      "image": ""
    },
    {
      "id": 82,
      "question": "Рустам дар Шоҳнома рамзи чӣ аст?",
      "options": [
        "Зебоӣ",
        "Хирад",
        "Қаҳрамонӣ ва ватандӯстӣ",
        "Бойгарӣ"
      ],
      "correctIndex": 2,
      "image": ""
    },    {
      "id": 83,
      "question": "Сам дар давраи кадом подшоҳ хизмат мекард?",
      "options": [
        "Фаридун",
        "Манучеҳр",
        "Ҷамшед",
        "Заҳҳок"
      ],
      "correctIndex": 1,
      "image": ""
    },
    {
      "id": 84,
      "question": "Сам бо кадом сифат машҳур буд?",
      "options": [
        "Хирадмандӣ",
        "Қувваи ҷисмонӣ",
        "Содагӣ",
        "Сарват"
      ],
      "correctIndex": 1,
      "image": ""
    },
    {
      "id": 85,
      "question": "Зал пас аз бозгашт аз кӯҳ дар куҷо зиндагӣ кард?",
      "options": [
        "Дар Турон",
        "Дар Зобулистон",
        "Дар Ҳинд",
        "Дар Миср"
      ],
      "correctIndex": 1,
      "image": ""
    },
    {
      "id": 86,
      "question": "Зобулистон бо кадом қаҳрамон бештар вобаста аст?",
      "options": [
        "Фаридун",
        "Рустам",
        "Манучеҳр",
        "Таҳмурас"
      ],
      "correctIndex": 1,
      "image": ""
    },
    {
      "id": 87,
      "question": "Рудоба бо кадом хислат машҳур аст?",
      "options": [
        "Ҷасорат ва ақл",
        "Хомӯшӣ",
        "Тундхӯӣ",
        "Тарс"
      ],
      "correctIndex": 0,
      "image": ""
    },
    {
      "id": 88,
      "question": "Синдухт кист?",
      "options": [
        "Модари Зал",
        "Модари Рудоба",
        "Хоҳари Сам",
        "Зани Манучеҳр"
      ],
      "correctIndex": 1,
      "image": ""
    },
    {
      "id": 89,
      "question": "Синдухт барои сулҳ бо кӣ мулоқот кард?",
      "options": [
        "Манучеҳр",
        "Сам",
        "Фаридун",
        "Зал"
      ],
      "correctIndex": 1,
      "image": ""
    },
    {
      "id": 90,
      "question": "Сам дар баробари издивоҷи Зал чӣ мавқеъ гирифт?",
      "options": [
        "Мухолифат кард",
        "Розигӣ дод",
        "Хабар надошт",
        "Ҷанг оғоз кард"
      ],
      "correctIndex": 1,
      "image": ""
    },
    {
      "id": 91,
      "question": "Кадом подшоҳ ниҳоят издивоҷи Зал ва Рудобаро пазируфт?",
      "options": [
        "Сам",
        "Фаридун",
        "Манучеҳр",
        "Ҷамшед"
      ],
      "correctIndex": 2,
      "image": ""
    },
    {
      "id": 92,
      "question": "Рустам дар кадом сарзамин ба воя расид?",
      "options": [
        "Эрон",
        "Зобулистон",
        "Турон",
        "Ҳинд"
      ],
      "correctIndex": 1,
      "image": ""
    },
    {
      "id": 93,
      "question": "Кадом хусусият Рустамро аз дигарон ҷудо мекард?",
      "options": [
        "Зебоӣ",
        "Қувва ва далерӣ",
        "Бойгарӣ",
        "Хомӯшӣ"
      ],
      "correctIndex": 1,
      "image": ""
    },
    {
      "id": 94,
      "question": "Рустам дар ҷавонӣ бештар бо чӣ машғул буд?",
      "options": [
        "Илм",
        "Ҷанг ва шикор",
        "Тиҷорат",
        "Саёҳат"
      ],
      "correctIndex": 1,
      "image": ""
    },
    {
      "id": 95,
      "question": "Аспи Рахш дар кадом ҳолат хатарро эҳсос мекард?",
      "options": [
        "Ҳангоми хоб",
        "Ҳангоми ҷанг",
        "Ҳангоми танҳоӣ",
        "Ҳангоми борон"
      ],
      "correctIndex": 1,
      "image": ""
    },
    {
      "id": 96,
      "question": "Рахш дар чанд маврид ҷони Рустамро наҷот дод?",
      "options": [
        "Як бор",
        "Ду бор",
        "Бисёр бор",
        "Ҳеҷ гоҳ"
      ],
      "correctIndex": 2,
      "image": ""
    },
    {
      "id": 97,
      "question": "Дар Шоҳнома қаҳрамон одатан бо кадом сифат ситоиш мешавад?",
      "options": [
        "Бойгарӣ",
        "Зиракӣ",
        "Далерӣ ва вафо",
        "Зебоӣ"
      ],
      "correctIndex": 2,
      "image": ""
    },
    {
      "id": 98,
      "question": "Фирдавсӣ дар Шоҳнома бештар кадом арзишро тарғиб мекунад?",
      "options": [
        "Ҳила",
        "Зӯрӣ",
        "Адолат ва хирад",
        "Сарват"
      ],
      "correctIndex": 2,
      "image": ""
    },
    {
      "id": 99,
      "question": "Шоҳнома пеш аз ҳама кадом навъи асар аст?",
      "options": [
        "Ғазал",
        "Роман",
        "Достони ҳамосӣ",
        "Қиссаи кӯтоҳ"
      ],
      "correctIndex": 2,
      "image": ""
    },
    {
      "id": 100,
      "question": "Шоҳнома барои мардуми форсу тоҷик чӣ аҳамият дорад?",
      "options": [
        "Танҳо таърихӣ",
        "Танҳо адабӣ",
        "Мероси миллӣ ва фарҳангӣ",
        "Фақат афсона"
      ],
      "correctIndex": 2,
      "image": ""
    }
  ]
}
